docs/source/conf.py
examples/async_echo.py
examples/deploy_run_echo.py
examples/invoke_echo.py
examples/run_echo.py
examples/run_mean.py
examples/user_encrypt.py
examples/echo/app.py
examples/mean/app.py
pycape/__init__.py
pycape/_attestation.py
pycape/_attestation_test.py
pycape/_config.py
pycape/_enclave_encrypt.py
pycape/_enclave_encrypt_test.py
pycape/cape.py
pycape/cape_encrypt.py
pycape/cape_test.py
pycape/function_ref.py
pycape/function_ref_test.py
pycape/token.py
pycape/experimental/__init__.py
pycape/experimental/cli.py
pycape-3.1.1.dist-info/LICENSE
pycape-3.1.1.dist-info/METADATA
pycape-3.1.1.dist-info/NOTICE
pycape-3.1.1.dist-info/WHEEL
pycape-3.1.1.dist-info/top_level.txt
pycape-3.1.1.dist-info/RECORD
