Metadata-Version: 2.1
Name: pycape
Version: 3.1.1
Summary: The Cape Privacy Python SDK
Author-email: Cape Privacy <contact@capeprivacy.com>
License: Apache License
Project-URL: repository, https://github.com/capeprivacy/pycape
Classifier: Programming Language :: Python :: 3
Classifier: License :: OSI Approved :: Apache Software License
Classifier: Development Status :: 3 - Alpha
Classifier: Operating System :: OS Independent
Classifier: Topic :: Scientific/Engineering
Classifier: Topic :: Security :: Cryptography
Requires-Python: >=3.7
License-File: LICENSE
License-File: NOTICE
Requires-Dist: cbor2
Requires-Dist: hybrid-pke
Requires-Dist: websockets
Requires-Dist: pyOpenSSL
Requires-Dist: cose
Requires-Dist: requests
Requires-Dist: serdio
Requires-Dist: synchronicity (<0.3.0)
